DropdownExtension/__init__.py
DropdownExtension/_version.py
dropdownextension-0.1.0.data/data/share/jupyter/labextensions/DropdownExtension/build_log.json
dropdownextension-0.1.0.data/data/share/jupyter/labextensions/DropdownExtension/package.json
dropdownextension-0.1.0.data/data/share/jupyter/labextensions/DropdownExtension/static/lib_index_js.c2de762d740da5c9dc45.js
dropdownextension-0.1.0.data/data/share/jupyter/labextensions/DropdownExtension/static/lib_index_js.c2de762d740da5c9dc45.js.map
dropdownextension-0.1.0.data/data/share/jupyter/labextensions/DropdownExtension/static/remoteEntry.8229d19e105708715dc6.js
dropdownextension-0.1.0.data/data/share/jupyter/labextensions/DropdownExtension/static/remoteEntry.8229d19e105708715dc6.js.map
dropdownextension-0.1.0.data/data/share/jupyter/labextensions/DropdownExtension/static/style.js
dropdownextension-0.1.0.data/data/share/jupyter/labextensions/DropdownExtension/static/style_index_js.cbc3120cc54f1dea0272.js
dropdownextension-0.1.0.data/data/share/jupyter/labextensions/DropdownExtension/static/style_index_js.cbc3120cc54f1dea0272.js.map
dropdownextension-0.1.0.data/data/share/jupyter/labextensions/DropdownExtension/static/vendors-node_modules_octokit_core_dist-web_index_js.a5861cd129f211d76400.js
dropdownextension-0.1.0.data/data/share/jupyter/labextensions/DropdownExtension/static/vendors-node_modules_octokit_core_dist-web_index_js.a5861cd129f211d76400.js.map
dropdownextension-0.1.0.data/data/share/jupyter/labextensions/DropdownExtension/static/vendors-node_modules_octokit_rest_dist-web_index_js.aaa8147c12ce8630a5ea.js
dropdownextension-0.1.0.data/data/share/jupyter/labextensions/DropdownExtension/static/vendors-node_modules_octokit_rest_dist-web_index_js.aaa8147c12ce8630a5ea.js.map
dropdownextension-0.1.0.data/data/share/jupyter/labextensions/DropdownExtension/install.json
dropdownextension-0.1.0.dist-info/METADATA
dropdownextension-0.1.0.dist-info/WHEEL
dropdownextension-0.1.0.dist-info/licenses/LICENSE
dropdownextension-0.1.0.dist-info/RECORD
